ibmdbpy/__init__.py
ibmdbpy/aggregation.py
ibmdbpy/base.py
ibmdbpy/exceptions.py
ibmdbpy/filtering.py
ibmdbpy/frame.py
ibmdbpy/geoFrame.py
ibmdbpy/geoSeries.py
ibmdbpy/indexing.py
ibmdbpy/internals.py
ibmdbpy/series.py
ibmdbpy/sql.py
ibmdbpy/statistics.py
ibmdbpy/utils.py
ibmdbpy/feature_selection/__init__.py
ibmdbpy/feature_selection/chisquared.py
ibmdbpy/feature_selection/correlation.py
ibmdbpy/feature_selection/discretize.py
ibmdbpy/feature_selection/entropy.py
ibmdbpy/feature_selection/gain_ratio.py
ibmdbpy/feature_selection/gini.py
ibmdbpy/feature_selection/info_gain.py
ibmdbpy/feature_selection/private.py
ibmdbpy/feature_selection/symmetric_uncertainty.py
ibmdbpy/feature_selection/tstats.py
ibmdbpy/learn/__init__.py
ibmdbpy/learn/association_rules.py
ibmdbpy/learn/kmeans.py
ibmdbpy/learn/naive_bayes.py
ibmdbpy/sampledata/__init__.py
ibmdbpy/sampledata/iris.py
ibmdbpy/sampledata/iris.txt
ibmdbpy/sampledata/swiss.py
ibmdbpy/sampledata/swiss.txt
ibmdbpy/sampledata/titanic.py
ibmdbpy/sampledata/titanic.txt
ibmdbpy-0.1.6.post1.dist-info/LICENSE.txt
ibmdbpy-0.1.6.post1.dist-info/METADATA
ibmdbpy-0.1.6.post1.dist-info/WHEEL
ibmdbpy-0.1.6.post1.dist-info/top_level.txt
ibmdbpy-0.1.6.post1.dist-info/RECORD
