Metadata-Version: 2.1
Name: ibmdbpy
Version: 0.1.6.post1
Summary: A Pandas-like SQL-wrapper for in-database analytics with IBM Db2 Warehouse.
Home-page: https://github.com/ibmdbanalytics/ibmdbpy
Author: IBM Corp.
Author-email: Toni.Bollinger@de.ibm.com
License: BSD
Keywords: data analytics database development IBM Db2 Warehouse pandas scikitlearn scalability machine-learning knowledge discovery
Classifier: Development Status :: 7 - Inactive
Classifier: Intended Audience :: Developers
Classifier: Intended Audience :: Education
Classifier: Intended Audience :: End Users/Desktop
Classifier: Intended Audience :: Information Technology
Classifier: Intended Audience :: Science/Research
Classifier: Topic :: Software Development :: Build Tools
Classifier: License :: OSI Approved :: BSD License
Classifier: Operating System :: MacOS :: MacOS X
Classifier: Operating System :: Microsoft :: Windows
Classifier: Operating System :: POSIX
Classifier: Natural Language :: English
Classifier: Programming Language :: Python :: 2.7
Classifier: Programming Language :: Python :: 3
Classifier: Programming Language :: Python :: 3.2
Classifier: Programming Language :: Python :: 3.3
Classifier: Programming Language :: Python :: 3.4
Classifier: Programming Language :: Python :: 3.5
Classifier: Programming Language :: Python :: 3.6
Classifier: Programming Language :: Python :: Implementation :: CPython
Classifier: Topic :: Database
Classifier: Topic :: Scientific/Engineering
Classifier: Topic :: Software Development
License-File: LICENSE.txt
Requires-Dist: pandas
Requires-Dist: numpy
Requires-Dist: future
Requires-Dist: six
Requires-Dist: pypyodbc
Requires-Dist: lazy
Provides-Extra: doc
Requires-Dist: sphinx ; extra == 'doc'
Requires-Dist: ipython ; extra == 'doc'
Requires-Dist: numpydoc ; extra == 'doc'
Requires-Dist: sphinx-rtd-theme ; extra == 'doc'
Provides-Extra: jdbc
Requires-Dist: JayDeBeApi ==1.* ; extra == 'jdbc'
Requires-Dist: Jpype1 ==0.6.3 ; extra == 'jdbc'
Provides-Extra: test
Requires-Dist: pytest ; extra == 'test'
Requires-Dist: flaky ==3.4.0 ; extra == 'test'
